ens/__init__.py
ens/abis.py
ens/auto.py
ens/constants.py
ens/contract_data.py
ens/exceptions.py
ens/main.py
ens/utils.py
platon/__init__.py
platon/debug.py
platon/eth.py
platon/main.py
platon/manager.py
platon/method.py
platon/module.py
platon/node.py
platon/pip.py
platon/ppos.py
platon/restricting.py
platon/types.py
platon/_utils/__init__.py
platon/_utils/admin.py
platon/_utils/contract_formatter.py
platon/_utils/delegate.py
platon/_utils/error_code.py
platon/_utils/inner_contract.py
platon/_utils/method_formatters.py
platon/_utils/normalizers.py
platon/_utils/slashing.py
platon/_utils/staking.py
platon/chains/__init__.py
platon/chains/http.py
platon/chains/ipc.py
platon/chains/nodedev.py
platon/chains/websocket.py
platon/chains/alaya/__init__.py
platon/chains/alaya/endpoints.py
platon/chains/alaya/mainnet.py
platon/chains/alaya/testnet.py
platon/chains/platon/__init__.py
platon/chains/platon/endpoints.py
platon/chains/platon/mainnet.py
platon/chains/platon/testnet.py
platon/middleware/__init__.py
platon/middleware/pythonic.py
platon/middleware/validation.py
platon/tools/__init__.py
platon/tools/benchmark/__init__.py
platon/tools/benchmark/main.py
platon/tools/benchmark/node.py
platon/tools/benchmark/reporting.py
platon/tools/benchmark/utils.py
platon/tools/pytest_platon/__init__.py
platon/tools/pytest_platon/_utils.py
platon/tools/pytest_platon/deployer.py
platon/tools/pytest_platon/exceptions.py
platon/tools/pytest_platon/linker.py
platon/tools/pytest_platon/plugins.py
platon_py-2.0.1.dist-info/LICENSE
platon_py-2.0.1.dist-info/METADATA
platon_py-2.0.1.dist-info/WHEEL
platon_py-2.0.1.dist-info/entry_points.txt
platon_py-2.0.1.dist-info/top_level.txt
platon_py-2.0.1.dist-info/RECORD
