Metadata-Version: 2.1
Name: platon-py
Version: 2.0.1
Summary: platon.py
Home-page: https://github.com/PlatONNetwork/platon.py
Author: ssdut.steven
Author-email: ssdut.steven@gmail.com
License: MIT
Keywords: platon
Classifier: Development Status :: 5 - Production/Stable
Classifier: Intended Audience :: Developers
Classifier: License :: OSI Approved :: MIT License
Classifier: Natural Language :: English
Classifier: Programming Language :: Python :: 3
Classifier: Programming Language :: Python :: 3.6
Classifier: Programming Language :: Python :: 3.7
Classifier: Programming Language :: Python :: 3.8
Classifier: Programming Language :: Python :: 3.9
Requires-Python: >=3.6,<4
License-File: LICENSE
Requires-Dist: platon-typing (>=1.2.0)
Requires-Dist: platon-utils (>=1.2.1)
Requires-Dist: web3 (<6,>=5.23.0)
Requires-Dist: pywin32 (>=223) ; platform_system == "Windows"
Requires-Dist: typing-extensions (>=4.0.0) ; python_version < "3.8"
Provides-Extra: dev
Requires-Dist: platon-tester[py-evm] (>=1.2.0) ; extra == 'dev'
Requires-Dist: flake8 (>=6.0.0) ; extra == 'dev'
Requires-Dist: isort (>=5.0.0) ; extra == 'dev'
Requires-Dist: mypy (>=1.0.0) ; extra == 'dev'
Requires-Dist: mock ; extra == 'dev'
Requires-Dist: sphinx-better-theme (>=0.1.4) ; extra == 'dev'
Requires-Dist: click (>=8.0) ; extra == 'dev'
Requires-Dist: pytest (>=6.0.0) ; extra == 'dev'
Requires-Dist: sphinx (<7,>=4.0) ; extra == 'dev'
Requires-Dist: sphinx-rtd-theme (>=1.0.0) ; extra == 'dev'
Requires-Dist: towncrier (>=22.0) ; extra == 'dev'
Requires-Dist: wheel ; extra == 'dev'
Requires-Dist: bumpversion ; extra == 'dev'
Requires-Dist: flaky (>=3.7.0) ; extra == 'dev'
Requires-Dist: hypothesis (>=6.0.0) ; extra == 'dev'
Requires-Dist: pytest (<7,>=6.2.4) ; extra == 'dev'
Requires-Dist: pytest-asyncio (>=0.21.0) ; extra == 'dev'
Requires-Dist: pytest-mock (>=3.0.0) ; extra == 'dev'
Requires-Dist: pytest-pythonpath (>=0.3) ; extra == 'dev'
Requires-Dist: pytest-watch (>=4.2.0) ; extra == 'dev'
Requires-Dist: pytest-xdist (>=3.0.0) ; extra == 'dev'
Requires-Dist: setuptools (>=65.6.3) ; extra == 'dev'
Requires-Dist: tox (>=4.0.0) ; extra == 'dev'
Requires-Dist: tqdm (>=4.60.0) ; extra == 'dev'
Requires-Dist: twine (>=4.0.0) ; extra == 'dev'
Requires-Dist: when-changed (>=0.3.0) ; extra == 'dev'
Provides-Extra: docs
Requires-Dist: mock ; extra == 'docs'
Requires-Dist: sphinx-better-theme (>=0.1.4) ; extra == 'docs'
Requires-Dist: click (>=8.0) ; extra == 'docs'
Requires-Dist: pytest (>=6.0.0) ; extra == 'docs'
Requires-Dist: sphinx (<7,>=4.0) ; extra == 'docs'
Requires-Dist: sphinx-rtd-theme (>=1.0.0) ; extra == 'docs'
Requires-Dist: towncrier (>=22.0) ; extra == 'docs'
Requires-Dist: wheel ; extra == 'docs'
Provides-Extra: linter
Requires-Dist: flake8 (>=6.0.0) ; extra == 'linter'
Requires-Dist: isort (>=5.0.0) ; extra == 'linter'
Requires-Dist: mypy (>=1.0.0) ; extra == 'linter'
Provides-Extra: tester
Requires-Dist: platon-tester[py-evm] (>=1.2.0) ; extra == 'tester'
